  
{
    "users": [
      {
        "photo":"",
        "name": "Alex Murphy",
        "age": "20",
        "gender": "Male"
      },
      {
        "photo":"",
        "name": "Ben Parker",
        "age": "21",
        "gender": "Male"
      },
      {
        "photo":"",
        "name": "Charlie Howard",
        "age": "22",
        "gender": "Male"
      },
      {
        "photo":"",
        "name": "Daxter Turner",
        "age": "22",
        "gender": "Male"
      },
      {
        "photo":"",
        "name": "Ellington James",
        "age": "25",
        "gender": "Male"
      },
      {
        "photo":"",
        "name": "Abbie Gordon",
        "age": "20",
        "gender": "Female"
      },
      {
        "photo":"",
        "name": "Billie Jean",
        "age": "23",
        "gender": "Female"
      },
      {
        "photo":"",
        "name": "Charlene Carlos",
        "age": "26",
        "gender": "Female"
      },
      {
        "photo":"",
        "name": "Danielle Hexter",
        "age": "23",
        "gender": "Female"
      },
      {
        "photo":"",
        "name": "Emma Gannon",
        "age": "21",
        "gender": "Female"
      }
    ]
  }
